Workbook

Sheet Data
A1: Name of product as you would like it to appear on Find Software Suitable for Making Tax Digital for Income Tax gov.uk webpage | B1: name
A2: Please provide your company contact details as they should be displayed for customers | B2: phone
A3: Please provide your company email address as it should be displayed for customers | B3: email
A4: URL link to be used to direct customers to your website - preference is to a making Tax Digital for Income Tax specific page | B4: website
A5: Please insert link to your Accessibility Statement -if available on your website | B5: accessibilityStatementLink
B6: filters
A7: Does the vendor product include a Free Version? | B7: free-version
A8: Does the vendor product support Sole Trader income source? | B8: sole-trader
A9: Does the vendor product support UK Property income source? | B9: uk-property
A10: Does the vendor product support Foreign Property income source? | B10: overseas-property
A11: Is the vendor product Record keeping software? | B11: record-keeping
A12: Is the vendor product Bridging software? | B12: bridging
A13: Does your Making Tax Digital for Income Tax product also support VAT? | B13: vat
A14: Does the vendor product support Quarterly Submissions? | B14: quarterly-updates
A15: Does the vendor product support Self assessment tax return? | B15: tax-return
A16: Does the vendor product support Standard accounting periods - 6th April to 5th April? | B16: standard-update-periods
A17: Does the vendor product support Calendar accounting periods - 1st April to 31st March? | B17: calendar-update-periods
A18: Does the vendor product support Construction Industry Scheme income source? | B18: construction-industry-scheme
... A38: Is the vendor product suitable for use by an Agent? | B38: agent

Sheet Json Output
A1: =IF(ISBLANK(Data!A1),"",Data!B1) -> name | B1: =IF(ISBLANK(Data!C1),"",Data!C1) | D1: =CONCATENATE(CONCATENATE("""",A1,""""), ": ", CONCATENATE("""",B1,"""")) -> "name": "" | F1: =CONCATENATE("{",_xlfn.TEXTJOIN(",",TRUE,D1:D37),"}") -> {"name": "","phone": "","email": "","website": "","accessibilityStatementLink": "","filters": []}
A2: =IF(ISBLANK(Data!A2),"",Data!B2) -> phone | B2: =IF(ISBLANK(Data!C2),"",Data!C2) | D2: =CONCATENATE(CONCATENATE("""",A2,""""), ": ", CONCATENATE("""",B2,"""")) -> "phone": ""
A3: =IF(ISBLANK(Data!A3),"",Data!B3) -> email | B3: =IF(ISBLANK(Data!C3),"",Data!C3) | D3: =CONCATENATE(CONCATENATE("""",A3,""""), ": ", CONCATENATE("""",B3,"""")) -> "email": ""
A4: =IF(ISBLANK(Data!A4),"",Data!B4) -> website | B4: =IF(ISBLANK(Data!C4),"",Data!C4) | D4: =CONCATENATE(CONCATENATE("""",A4,""""), ": ", CONCATENATE("""",B4,"""")) -> "website": ""
A5: =IF(ISBLANK(Data!A5),"",Data!B5) -> accessibilityStatementLink | B5: =IF(ISBLANK(Data!C5),"",Data!C5) | D5: =CONCATENATE(CONCATENATE("""",A5,""""), ": ", CONCATENATE("""",B5,"""")) -> "accessibilityStatementLink": ""
A7: =IF(ISBLANK(Data!A6),"",Data!B6) | B7: =IF(ISBLANK(Data!C6),"",Data!C6) | D7: =_xlfn.CONCAT("""filters""", ": [", _xlfn.TEXTJOIN(",",TRUE,C8:C45),"]") -> "filters": []
A8: =IF(ISBLANK(Data!A7),"",Data!B7) -> free-version | B8: =IF(ISBLANK(Data!C7),"",Data!C7) | C8: =IF(B8=TRUE,CONCATENATE("""",A8,""""),"")
A9: =IF(ISBLANK(Data!A8),"",Data!B8) -> sole-trader | B9: =IF(ISBLANK(Data!C8),"",Data!C8) | C9: =IF(B9=TRUE,CONCATENATE("""",A9,""""),"")
A10: =IF(ISBLANK(Data!A9),"",Data!B9) -> uk-property | B10: =IF(ISBLANK(Data!C9),"",Data!C9) | C10: =IF(B10=TRUE,CONCATENATE("""",A10,""""),"")
A11: =IF(ISBLANK(Data!A10),"",Data!B10) -> overseas-property | B11: =IF(ISBLANK(Data!C10),"",Data!C10) | C11: =IF(B11=TRUE,CONCATENATE("""",A11,""""),"")
A12: =IF(ISBLANK(Data!A11),"",Data!B11) -> record-keeping | B12: =IF(ISBLANK(Data!C11),"",Data!C11) | C12: =IF(B12=TRUE,CONCATENATE("""",A12,""""),"")
A13: =IF(ISBLANK(Data!A12),"",Data!B12) -> bridging | B13: =IF(ISBLANK(Data!C12),"",Data!C12) | C13: =IF(B13=TRUE,CONCATENATE("""",A13,""""),"")
A14: =IF(ISBLANK(Data!A13),"",Data!B13) -> vat | B14: =IF(ISBLANK(Data!C13),"",Data!C13) | C14: =IF(B14=TRUE,CONCATENATE("""",A14,""""),"")
A15: =IF(ISBLANK(Data!A14),"",Data!B14) -> quarterly-updates | B15: =IF(ISBLANK(Data!C14),"",Data!C14) | C15: =IF(B15=TRUE,CONCATENATE("""",A15,""""),"")
A16: =IF(ISBLANK(Data!A15),"",Data!B15) -> tax-return | B16: =IF(ISBLANK(Data!C15),"",Data!C15) | C16: =IF(B16=TRUE,CONCATENATE("""",A16,""""),"")
A17: =IF(ISBLANK(Data!A16),"",Data!B16) -> standard-update-periods | B17: =IF(ISBLANK(Data!C16),"",Data!C16) | C17: =IF(B17=TRUE,CONCATENATE("""",A17,""""),"")
A18: =IF(ISBLANK(Data!A17),"",Data!B17) -> calendar-update-periods | B18: =IF(ISBLANK(Data!C17),"",Data!C17) | C18: =IF(B18=TRUE,CONCATENATE("""",A18,""""),"")
A19: =IF(ISBLANK(Data!A18),"",Data!B18) -> construction-industry-scheme | B19: =IF(ISBLANK(Data!C18),"",Data!C18) | C19: =IF(B19=TRUE,CONCATENATE("""",A19,""""),"")
... A39: =IF(ISBLANK(Data!A38),"",Data!B38) -> agent | B39: =IF(ISBLANK(Data!C38),"",Data!C38) | C39: =IF(B39=TRUE,CONCATENATE("""",A39,""""),"")
A40: =IF(ISBLANK(Data!A40),"",Data!B40) | B40: =IF(ISBLANK(Data!C40),"",Data!C40) | C40: =IF(B40=TRUE,CONCATENATE("""",A40,""""),"")
A41: =IF(ISBLANK(Data!A41),"",Data!B41) | B41: =IF(ISBLANK(Data!C41),"",Data!C41)
A42: =IF(ISBLANK(Data!A42),"",Data!B42) | B42: =IF(ISBLANK(Data!C42),"",Data!C42)
A43: =IF(ISBLANK(Data!A43),"",B43)
A44: =IF(ISBLANK(Data!A44),"",B44)
A45: =IF(ISBLANK(Data!A45),"",B45)
A46: =IF(ISBLANK(Data!A46),"",B46)
A47: =IF(ISBLANK(Data!A47),"",B47)
A48: =IF(ISBLANK(Data!A48),"",B48)
A49: =IF(ISBLANK(Data!A49),"",B49)
A50: =IF(ISBLANK(Data!A50),"",B50)
A51: =IF(ISBLANK(Data!A51),"",B51)
A52: =IF(ISBLANK(Data!A52),"",B52)
A53: =IF(ISBLANK(Data!A53),"",B53)
A54: =IF(ISBLANK(Data!A54),"",B54)
... A63: =IF(ISBLANK(Data!A63),"",B63)
