Workbook

Sheet Data
A1: Name of product as you would like it to appear on Find Software Suitable for Making Tax Digital for Income Tax gov.uk webpage | B1: name
A2: Please provide your company contact details as they should be displayed for customers | B2: phone
A3: Please provide your company email address as it should be displayed for customers | B3: email
A4: URL link to be used to direct customers to your website - preference is to a making Tax Digital for Income Tax specific page | B4: website
A5: Please insert link to your Accessibility Statement -if available on your website | B5: accessibilityStatementLink
B6: filters
A7: Does the vendor product include a Free Version? | B7: free-version
A8: Does the vendor product support Sole Trader income source? | B8: sole-trader
A9: Does the vendor product support UK Property income source? | B9: uk-property
A10: Does the vendor product support Foreign Property income source? | B10: overseas-property
A11: Is the vendor product Record keeping software? | B11: record-keeping
A12: Is the vendor product Bridging software? | B12: bridging
A13: Does your Making Tax Digital for Income Tax product also support VAT? | B13: vat
A14: Does the vendor product support Quarterly Submissions? | B14: quarterly-updates
A15: Does the vendor product support Self assessment tax return? | B15: tax-return
A16: Does the vendor product support Standard accounting periods - 6th April to 5th April? | B16: standard-update-periods
A17: Does the vendor product support Calendar accounting periods - 1st April to 31st March? | B17: calendar-update-periods
A18: Does the vendor product support Construction Industry Scheme income source? | B18: construction-industry-scheme
... A48: Is the vendor product language English? | B48: english

Sheet Json Output
A1: =IF(ISBLANK(Data!A1),"",Data!B1) -> name | B1: =IF(ISBLANK(Data!C1),"",Data!C1) | D1: =CONCATENATE(CONCATENATE("""",A1,""""), ": ", CONCATENATE("""",B1,"""")) -> "name": "" | F1: =CONCATENATE("{",_xlfn.TEXTJOIN(",",TRUE,D1:D38),"}") -> {"name": "","phone": "","email": "","website": "","accessibilityStatementLink": "","filters": {}}
A2: =IF(ISBLANK(Data!A2),"",Data!B2) -> phone | B2: =IF(ISBLANK(Data!C2),"",Data!C2) | D2: =CONCATENATE(CONCATENATE("""",A2,""""), ": ", CONCATENATE("""",B2,"""")) -> "phone": ""
A3: =IF(ISBLANK(Data!A3),"",Data!B3) -> email | B3: =IF(ISBLANK(Data!C3),"",Data!C3) | D3: =CONCATENATE(CONCATENATE("""",A3,""""), ": ", CONCATENATE("""",B3,"""")) -> "email": ""
A4: =IF(ISBLANK(Data!A4),"",Data!B4) -> website | B4: =IF(ISBLANK(Data!C4),"",Data!C4) | D4: =CONCATENATE(CONCATENATE("""",A4,""""), ": ", CONCATENATE("""",B4,"""")) -> "website": ""
A5: =IF(ISBLANK(Data!A5),"",Data!B5) -> accessibilityStatementLink | B5: =IF(ISBLANK(Data!C5),"",Data!C5) | D5: =CONCATENATE(CONCATENATE("""",A5,""""), ": ", CONCATENATE("""",B5,"""")) -> "accessibilityStatementLink": ""
A7: =IF(ISBLANK(Data!A6),"",Data!B6) | B7: =IF(ISBLANK(Data!C6),"",Data!C6) | D7: =_xlfn.CONCAT("""filters""", ": {", _xlfn.TEXTJOIN(",",TRUE,C8:C63),"}") -> "filters": {}
A8: =IF(ISBLANK(Data!A7),"",Data!B7) -> free-version | B8: =IF(ISBLANK(Data!C7),"",Data!C7) | C8: =IF(OR(B8="Available",B8="Intended"),CONCATENATE("""",A8,"""",": ","""",B8,""""),"")
A9: =IF(ISBLANK(Data!A8),"",Data!B8) -> sole-trader | B9: =IF(ISBLANK(Data!C8),"",Data!C8) | C9: =IF(OR(B9="Available",B9="Intended"),CONCATENATE("""",A9,"""",": ","""",B9,""""),"")
A10: =IF(ISBLANK(Data!A9),"",Data!B9) -> uk-property | B10: =IF(ISBLANK(Data!C9),"",Data!C9) | C10: =IF(OR(B10="Available",B10="Intended"),CONCATENATE("""",A10,"""",": ","""",B10,""""),"")
A11: =IF(ISBLANK(Data!A10),"",Data!B10) -> overseas-property | B11: =IF(ISBLANK(Data!C10),"",Data!C10) | C11: =IF(OR(B11="Available",B11="Intended"),CONCATENATE("""",A11,"""",": ","""",B11,""""),"")
A12: =IF(ISBLANK(Data!A11),"",Data!B11) -> record-keeping | B12: =IF(ISBLANK(Data!C11),"",Data!C11) | C12: =IF(OR(B12="Available",B12="Intended"),CONCATENATE("""",A12,"""",": ","""",B12,""""),"")
A13: =IF(ISBLANK(Data!A12),"",Data!B12) -> bridging | B13: =IF(ISBLANK(Data!C12),"",Data!C12) | C13: =IF(OR(B13="Available",B13="Intended"),CONCATENATE("""",A13,"""",": ","""",B13,""""),"")
A14: =IF(ISBLANK(Data!A13),"",Data!B13) -> vat | B14: =IF(ISBLANK(Data!C13),"",Data!C13) | C14: =IF(OR(B14="Available",B14="Intended"),CONCATENATE("""",A14,"""",": ","""",B14,""""),"")
A15: =IF(ISBLANK(Data!A14),"",Data!B14) -> quarterly-updates | B15: =IF(ISBLANK(Data!C14),"",Data!C14) | C15: =IF(OR(B15="Available",B15="Intended"),CONCATENATE("""",A15,"""",": ","""",B15,""""),"")
A16: =IF(ISBLANK(Data!A15),"",Data!B15) -> tax-return | B16: =IF(ISBLANK(Data!C15),"",Data!C15) | C16: =IF(OR(B16="Available",B16="Intended"),CONCATENATE("""",A16,"""",": ","""",B16,""""),"")
A17: =IF(ISBLANK(Data!A16),"",Data!B16) -> standard-update-periods | B17: =IF(ISBLANK(Data!C16),"",Data!C16) | C17: =IF(OR(B17="Available",B17="Intended"),CONCATENATE("""",A17,"""",": ","""",B17,""""),"")
A18: =IF(ISBLANK(Data!A17),"",Data!B17) -> calendar-update-periods | B18: =IF(ISBLANK(Data!C17),"",Data!C17) | C18: =IF(OR(B18="Available",B18="Intended"),CONCATENATE("""",A18,"""",": ","""",B18,""""),"")
A19: =IF(ISBLANK(Data!A18),"",Data!B18) -> construction-industry-scheme | B19: =IF(ISBLANK(Data!C18),"",Data!C18) | C19: =IF(OR(B19="Available",B19="Intended"),CONCATENATE("""",A19,"""",": ","""",B19,""""),"")
... A63: =IF(ISBLANK(Data!A62),"",Data!B62) | B63: =IF(ISBLANK(Data!C62),"",Data!C62) | C63: =IF(OR(B63="Available",B63="Intended"),CONCATENATE("""",A63,"""",": ","""",B63,""""),"")
